nbsafety/__init__.py
nbsafety/_version.py
nbsafety/frontend.py
nbsafety/install.py
nbsafety/ipython_utils.py
nbsafety/line_magics.py
nbsafety/run_mode.py
nbsafety/safety.py
nbsafety/singletons.py
nbsafety/types.py
nbsafety/version.py
nbsafety/analysis/__init__.py
nbsafety/analysis/live_refs.py
nbsafety/analysis/mixins.py
nbsafety/analysis/resolved_symbols.py
nbsafety/analysis/slicing.py
nbsafety/analysis/symbol_edges.py
nbsafety/analysis/symbol_ref.py
nbsafety/analysis/utils.py
nbsafety/data_model/__init__.py
nbsafety/data_model/annotation_utils.py
nbsafety/data_model/code_cell.py
nbsafety/data_model/data_symbol.py
nbsafety/data_model/namespace.py
nbsafety/data_model/scope.py
nbsafety/data_model/sizing.py
nbsafety/data_model/timestamp.py
nbsafety/data_model/update_protocol.py
nbsafety/experimental/__init__.py
nbsafety/experimental/dag.py
nbsafety/kernel/__init__.py
nbsafety/kernel/__main__.py
nbsafety/kernel/install.py
nbsafety/kernel/kernel.py
nbsafety/resources/kernel/kernel.json
nbsafety/resources/kernel/logo-32x32.png
nbsafety/resources/kernel/logo-64x64.png
nbsafety/resources/labextension/package.json
nbsafety/resources/labextension/static/549.d955ad08e799fbf9e11e.js
nbsafety/resources/labextension/static/568.0d7ec8cf2063052d1369.js
nbsafety/resources/labextension/static/remoteEntry.22475428eabd2879586d.js
nbsafety/resources/labextension/static/style.js
nbsafety/resources/labextension/static/third-party-licenses.json
nbsafety/resources/nbextension/index.js
nbsafety/resources/nbextension/index.js.map
nbsafety/resources/nbextension/nbsafety.json
nbsafety/tracing/__init__.py
nbsafety/tracing/mutation_event.py
nbsafety/tracing/mutation_special_cases.py
nbsafety/tracing/nbsafety_tracer.py
nbsafety/tracing/safety_ast_rewriter.py
nbsafety/tracing/symbol_resolver.py
nbsafety/tracing/trace_stmt.py
nbsafety/tracing/utils.py
nbsafety/utils/__init__.py
nbsafety/utils/ast_utils.py
nbsafety/utils/misc_utils.py
nbsafety/utils/mixins.py
nbsafety-0.0.87.dist-info/LICENSE.txt
nbsafety-0.0.87.dist-info/METADATA
nbsafety-0.0.87.dist-info/WHEEL
nbsafety-0.0.87.dist-info/top_level.txt
nbsafety-0.0.87.dist-info/RECORD
