Metadata-Version: 2.1
Name: nbsafety
Version: 0.0.87
Summary: Fearless interactivity for Jupyter notebooks.
Home-page: https://github.com/nbsafety-project/nbsafety
Author: Stephen Macke
Author-email: stephen.macke@gmail.com
License: BSD-3-Clause
Platform: UNKNOWN
Classifier: Development Status :: 3 - Alpha
Classifier: Intended Audience :: Developers
Classifier: License :: OSI Approved :: BSD License
Classifier: Natural Language :: English
Classifier: Programming Language :: Python :: 3.6
Classifier: Programming Language :: Python :: 3.7
Classifier: Programming Language :: Python :: 3.8
Classifier: Programming Language :: Python :: 3.9
License-File: LICENSE.txt
Requires-Dist: astunparse
Requires-Dist: black
Requires-Dist: ipykernel
Requires-Dist: ipython (<8.0.0)
Requires-Dist: jupyter
Requires-Dist: jupyterlab (>=3.0)
Requires-Dist: mypy
Requires-Dist: nbclassic (>=0.2.8)
Requires-Dist: nest-asyncio
Requires-Dist: pyccolo (==0.0.27)
Requires-Dist: traitlets
